sigan/__init__.py
sigan/api/api.py
sigan/commands/command.py
sigan/config.json
sigan/config.py
sigan/constants.py
sigan/sigan.py
sigan/utils/display.py
sigan/utils/general_utils.py
sigan/utils/time_utils.py
sigan-0.1.22.dist-info/entry_points.txt
sigan-0.1.22.dist-info/METADATA
sigan-0.1.22.dist-info/WHEEL
sigan-0.1.22.dist-info/RECORD
