Metadata-Version: 2.1
Name: sigan
Version: 0.1.22
Summary: version update
Author: Earthquakoo
Author-email: cream5343@gmail.com
Requires-Python: >=3.9,<4.0
Classifier: Programming Language :: Python :: 3
Classifier: Programming Language :: Python :: 3.9
Classifier: Programming Language :: Python :: 3.10
Classifier: Programming Language :: Python :: 3.11
Requires-Dist: pymysql (>=1.1.0,<2.0.0)
Requires-Dist: python-dotenv (>=1.0.0,<2.0.0)
Requires-Dist: requests (>=2.31.0,<3.0.0)
Requires-Dist: rich (>=13.6.0,<14.0.0)
Requires-Dist: slack-sdk (>=3.23.0,<4.0.0)
Requires-Dist: sqlalchemy (>=2.0.21,<3.0.0)
Requires-Dist: typer[all] (>=0.9.0,<0.10.0)
